LICENSE
MANIFEST.in
README.md
setup.py
tap_criteo/__init__.py
tap_criteo/criteo.py
tap_criteo/discover.py
tap_criteo/endpoints.py
tap_criteo/sync.py
tap_criteo.egg-info/PKG-INFO
tap_criteo.egg-info/SOURCES.txt
tap_criteo.egg-info/dependency_links.txt
tap_criteo.egg-info/entry_points.txt
tap_criteo.egg-info/requires.txt
tap_criteo.egg-info/top_level.txt
tap_criteo/schemas/AdvertiserInfo.json
tap_criteo/schemas/Audiences.json
tap_criteo/schemas/Budgets.json
tap_criteo/schemas/CampaignBids.json
tap_criteo/schemas/CampaignStats.json
tap_criteo/schemas/Campaigns.json
tap_criteo/schemas/Categories.json
tap_criteo/schemas/Portfolio.json
tap_criteo/schemas/SellerBudgets.json
tap_criteo/schemas/SellerCampaignStats.json
tap_criteo/schemas/SellerCampaigns.json
tap_criteo/schemas/SellerStats.json
tap_criteo/schemas/Sellers.json
tap_criteo/schemas/Statistics.json